odoo/addons/l10n_br_product_contract/README.rst
odoo/addons/l10n_br_product_contract/__init__.py
odoo/addons/l10n_br_product_contract/__manifest__.py
odoo/addons/l10n_br_product_contract/demo/contract_template.xml
odoo/addons/l10n_br_product_contract/demo/product.xml
odoo/addons/l10n_br_product_contract/demo/sale_order.xml
odoo/addons/l10n_br_product_contract/i18n/l10n_br_product_contract.pot
odoo/addons/l10n_br_product_contract/models/__init__.py
odoo/addons/l10n_br_product_contract/models/sale_order.py
odoo/addons/l10n_br_product_contract/models/sale_order_line.py
odoo/addons/l10n_br_product_contract/readme/CONFIGURE.rst
odoo/addons/l10n_br_product_contract/readme/CONTRIBUTORS.rst
odoo/addons/l10n_br_product_contract/readme/CREDITS.rst
odoo/addons/l10n_br_product_contract/readme/DESCRIPTION.rst
odoo/addons/l10n_br_product_contract/readme/HISTORY.rst
odoo/addons/l10n_br_product_contract/readme/INSTALL.rst
odoo/addons/l10n_br_product_contract/readme/USAGE.rst
odoo/addons/l10n_br_product_contract/static/description/icon.png
odoo/addons/l10n_br_product_contract/static/description/index.html
odoo/addons/l10n_br_product_contract/tests/__init__.py
odoo/addons/l10n_br_product_contract/tests/test_l10n_br_product_contract.py
odoo12_addon_l10n_br_product_contract-12.0.1.0.0.99.dev20.dist-info/METADATA
odoo12_addon_l10n_br_product_contract-12.0.1.0.0.99.dev20.dist-info/WHEEL
odoo12_addon_l10n_br_product_contract-12.0.1.0.0.99.dev20.dist-info/top_level.txt
odoo12_addon_l10n_br_product_contract-12.0.1.0.0.99.dev20.dist-info/RECORD
